subresource_integrity.py
subresource_integrity-0.2.dist-info/DESCRIPTION.rst
subresource_integrity-0.2.dist-info/METADATA
subresource_integrity-0.2.dist-info/RECORD
subresource_integrity-0.2.dist-info/WHEEL
subresource_integrity-0.2.dist-info/metadata.json
subresource_integrity-0.2.dist-info/top_level.txt
