Metadata-Version: 2.0
Name: subresource-integrity
Version: 0.2
Summary: Create and parse HTML subresource integrity values
Home-page: https://github.com/moreati/subresource-integrity
Author: Alex Willmer
Author-email: alex@moreati.org.uk
License: BSD
Platform: UNKNOWN
Classifier: Development Status :: 3 - Alpha
Classifier: Intended Audience :: Developers
Classifier: License :: OSI Approved :: BSD License
Classifier: Programming Language :: Python :: 2.7
Classifier: Programming Language :: Python :: 3
Classifier: Programming Language :: Python :: 3.5
Classifier: Programming Language :: Python :: 3.6
Classifier: Programming Language :: Python :: 3.7
